tolbi/__init__.py
tolbi/middleware.py
tolbi_gis-1.0.3.dist-info/licenses/LICENSE
tolbi_gis-1.0.3.dist-info/METADATA
tolbi_gis-1.0.3.dist-info/WHEEL
tolbi_gis-1.0.3.dist-info/top_level.txt
tolbi_gis-1.0.3.dist-info/RECORD
