Metadata-Version: 2.4
Name: tolbi-gis
Version: 1.0.3
Summary: A Django middleware to explode GeoJSON files in requests.
Author: Tolbi
Author-email: Tolbi <dep.it@tolbico.com>
Requires-Python: >=3.7
License-File: LICENSE
Requires-Dist: Django>=3.2
Requires-Dist: geopandas
Dynamic: author
Dynamic: license-file
Dynamic: requires-python
